{
  "coc.preferences.formatOnSaveFiletypes": ["css", "markdown", "javascript", "graphql", "html", "yaml",  "json", "python"],

  // python config
  "python.linting.enabled": true,
  "python.linting.pylintEnabled": true,
  "jedi.enable": true,
  "jedi.startupMessage": false,
  "jedi.markupKindPreferred": "plaintext",
  "jedi.trace.server": "off",
  "jedi.jediSettings.autoImportModules": [],
  "jedi.jediSettings.caseInsensitiveCompletion": true,
  "jedi.jediSettings.debug": false,
  "jedi.executable.command": "jedi-language-server",
  "jedi.executable.args": [],
  "jedi.codeAction.nameExtractFunction": "jls_extract_def",
  "jedi.codeAction.nameExtractVariable": "jls_extract_var",
  "jedi.completion.disableSnippets": false,
  "jedi.completion.resolveEagerly": false,
  "jedi.completion.ignorePatterns": [],
  "jedi.diagnostics.enable": true,
  "jedi.diagnostics.didOpen": true,
  "jedi.diagnostics.didChange": true,
  "jedi.diagnostics.didSave": true,
  "jedi.hover.enable": true,
  "jedi.hover.disable.keyword.all": false,
  "jedi.hover.disable.keyword.names": [],
  "jedi.hover.disable.keyword.fullNames": [],
  "jedi.workspace.extraPaths": [],
  "jedi.workspace.symbols.maxSymbols": 20,
  "jedi.workspace.symbols.ignoreFolders": [
    ".nox",
    ".tox",
    ".venv",
    "__pycache__",
    "venv"
  ],

  "snippets.ultisnips.directories":
  [
    "UltiSnips",
    "~/.config/nvim/utils/snips"
  ],

  "languageserver": {
  },

  // php
  // "intelephense.stubs": ["MEMCACHED"]
  // check here https://github.com/yaegassy/coc-intelephense
  "intelephense.stubs" : [
    "apache",
    "bcmath",
    "bz2",
    "calendar",
    "com_dotnet",
    "Core",
    "ctype",
    "curl",
    "date",
    "dba",
    "dom",
    "enchant",
    "exif",
    "FFI",
    "fileinfo",
    "filter",
    "fpm",
    "ftp",
    "gd",
    "gettext",
    "gmp",
    "hash",
    "iconv",
    "imap",
    "intl",
    "json",
    "ldap",
    "libxml",
    "mbstring",
    "meta",
    "mysqli",
    "oci8",
    "odbc",
    "openssl",
    "pcntl",
    "pcre",
    "PDO",
    "pdo_ibm",
    "pdo_mysql",
    "pdo_pgsql",
    "pdo_sqlite",
    "pgsql",
    "Phar",
    "posix",
    "pspell",
    "readline",
    "Reflection",
    "session",
    "shmop",
    "SimpleXML",
    "snmp",
    "soap",
    "sockets",
    "sodium",
    "SPL",
    "sqlite3",
    "standard",
    "superglobals",
    "sysvmsg",
    "sysvsem",
    "sysvshm",
    "tidy",
    "tokenizer",
    "xml",
    "xmlreader",
    "xmlrpc",
    "xmlwriter",
    "xsl",
    "Zend OPcache",
    "zip",
    "zlib",
    "Memcached",
    "Memcache",
    "RedisCluster",
    "Redis",
    "Predis",
    "rand"
  ]
}
